google_analytics/__init__.py
google_analytics/middleware.py
google_analytics/tasks.py
google_analytics/test_runner.py
google_analytics/urls.py
google_analytics/utils.py
google_analytics/views.py
google_analytics/templatetags/__init__.py
google_analytics/templatetags/google_analytics_tags.py
google_analytics/tests/__init__.py
google_analytics/tests/test_ga.py
google_analytics/tests/test_templatetags_google_analytics_tags.py
django_google_analytics_app-6.0.0.dist-info/LICENSE
django_google_analytics_app-6.0.0.dist-info/METADATA
django_google_analytics_app-6.0.0.dist-info/WHEEL
django_google_analytics_app-6.0.0.dist-info/top_level.txt
django_google_analytics_app-6.0.0.dist-info/RECORD
