Metadata-Version: 2.1
Name: django-google-analytics-app
Version: 6.0.0
Summary: Django Google Analytics app allowing for server side/non-js tracking.
Home-page: http://github.com/praekelt/django-google-analytics
Author: Praekelt.org
Author-email: dev@praekelt.org
License: BSD
Keywords: django,google,analytics
Classifier: Development Status :: 5 - Production/Stable
Classifier: Framework :: Django
Classifier: Intended Audience :: Developers
Classifier: License :: OSI Approved :: BSD License
Classifier: Operating System :: OS Independent
Classifier: Programming Language :: Python :: 3
Classifier: Programming Language :: Python :: 3.6
Classifier: Programming Language :: Python :: 3.7
Classifier: Programming Language :: Python :: 3.8
Classifier: Programming Language :: Python :: 3.9
Classifier: Programming Language :: Python :: 3.10
Classifier: Programming Language :: Python :: 3.11
Classifier: Topic :: Internet :: WWW/HTTP :: Dynamic Content
Provides-Extra: test
Provides-Extra: lint
License-File: LICENSE
